agentmode/__init__.py
agentmode/connector_setup.py
agentmode/connectors.toml
agentmode/database.py
agentmode/logs.py
agentmode/mcp_server.py
agentmode/api/__init__.py
agentmode/api/api_connection.py
agentmode/api/filter_openapi_specs.py
agentmode/api/openapi_to_mcp_converter.py
agentmode/api/parse_openapi_specs.py
agentmode/api/connectors/Airflow.json
agentmode/api/connectors/Bitbucket.json
agentmode/api/connectors/Confluence.json
agentmode/api/connectors/Prefect.json
agentmode/api/connectors/__init__.py
agentmode/api/connectors/api_connector.py
agentmode/resources/log_config.json
agentmode/resources/css/custom.css
agentmode/resources/images/airflow.png
agentmode/resources/images/athena.png
agentmode/resources/images/bigquery.png
agentmode/resources/images/bitbucket.png
agentmode/resources/images/clickhouse.svg
agentmode/resources/images/cockroachdb.jpeg
agentmode/resources/images/cockroachdb.png
agentmode/resources/images/confluence.svg
agentmode/resources/images/databricks.svg
agentmode/resources/images/docker.svg
agentmode/resources/images/elastic.svg
agentmode/resources/images/github.png
agentmode/resources/images/github.svg
agentmode/resources/images/gitlab.svg
agentmode/resources/images/hive.svg
agentmode/resources/images/jira.svg
agentmode/resources/images/mariadb.svg
agentmode/resources/images/mysql.svg
agentmode/resources/images/neondb.svg
agentmode/resources/images/oracle.svg
agentmode/resources/images/postgresql.svg
agentmode/resources/images/prefect.svg
agentmode/resources/images/presto.svg
agentmode/resources/images/redshift.jpg
agentmode/resources/images/redshift.png
agentmode/resources/images/sap.svg
agentmode/resources/images/snowflake.svg
agentmode/resources/images/sql_server.png
agentmode/resources/images/sumo_logic.svg
agentmode/resources/images/supabase.svg
agentmode/resources/images/teradata.svg
agentmode/resources/images/timescale.svg
agentmode/resources/images/trino.svg
agentmode/resources/images/vitess.png
agentmode-0.1.16.dist-info/METADATA
agentmode-0.1.16.dist-info/WHEEL
agentmode-0.1.16.dist-info/entry_points.txt
agentmode-0.1.16.dist-info/RECORD
