Metadata-Version: 2.4
Name: agentmode
Version: 0.1.16
Summary: All-in-1 MCP server for developers
Project-URL: Homepage, https://www.agentmode.app
Keywords: ai,mcp
Requires-Python: >=3.12
Requires-Dist: aiomysql>=0.2.0
Requires-Dist: aioodbc>=0.5.0
Requires-Dist: aiotrino>=0.3.0
Requires-Dist: asyncpg>=0.30.0
Requires-Dist: click>=8.1.8
Requires-Dist: clickhouse-sqlalchemy>=0.3.2
Requires-Dist: greenlet>=3.2.0
Requires-Dist: httpx>=0.28.1
Requires-Dist: mcp[cli]>=1.6.0
Requires-Dist: oracledb>=3.1.0
Requires-Dist: pandas>=2.2.3
Requires-Dist: platformdirs>=4.3.7
Requires-Dist: presto-python-client>=0.8.4
Requires-Dist: pyathena[sqlalchemy]>=3.13.0
Requires-Dist: pyhive>=0.7.0
Requires-Dist: python-benedict[toml]>=0.34.1
Requires-Dist: snowflake-sqlalchemy>=1.7.3
Requires-Dist: sqlalchemy-bigquery>=1.13.0
Requires-Dist: sqlalchemy-cockroachdb>=2.0.2
Requires-Dist: sqlalchemy-hana>=3.0.2
Requires-Dist: sqlalchemy>=2.0.40
Requires-Dist: sqlglot[rs]>=26.16.0
Requires-Dist: starlette>=0.46.2
Requires-Dist: teradatasqlalchemy>=20.0.0.4
Requires-Dist: uvicorn>=0.34.1
